LICENSE
MANIFEST.in
README.rst
VERSION
setup.py
Flask_Webpack.egg-info/PKG-INFO
Flask_Webpack.egg-info/SOURCES.txt
Flask_Webpack.egg-info/dependency_links.txt
Flask_Webpack.egg-info/not-zip-safe
Flask_Webpack.egg-info/pbr.json
Flask_Webpack.egg-info/requires.txt
Flask_Webpack.egg-info/top_level.txt
flask_webpack/__init__.py